Orange3_Shangtang-0.1.0-py3.7-nspkg.pth
orangecontrib/shangtang/__init__.py
orangecontrib/shangtang/widgets/__init__.py
orangecontrib/shangtang/widgets/owFaceCompare.py
orangecontrib/shangtang/widgets/icons/face_compare.png
orangecontrib/shangtang/widgets/utils/__init__.py
orangecontrib/shangtang/widgets/utils/owShangtangApi.py
orangecontrib/shangtang/widgets/utils/utils.py
Orange3_Shangtang-0.1.0.dist-info/LICENSE
Orange3_Shangtang-0.1.0.dist-info/METADATA
Orange3_Shangtang-0.1.0.dist-info/WHEEL
Orange3_Shangtang-0.1.0.dist-info/entry_points.txt
Orange3_Shangtang-0.1.0.dist-info/namespace_packages.txt
Orange3_Shangtang-0.1.0.dist-info/top_level.txt
Orange3_Shangtang-0.1.0.dist-info/RECORD
