Metadata-Version: 2.1
Name: Orange3-Shangtang
Version: 0.1.0
Summary: 商汤教育人工智能 API 橙现智能Orange 图形化实现的插件
Home-page: https://github.com/szzyiit/orange3-shangtang
Author: SZZYIIT
Author-email: gengy@zhaoyang.org.cn
License: UNKNOWN
Keywords: orange3 add-on
Platform: UNKNOWN
Requires-Dist: Orange3-zh (>=3.21.0)
